wikipedia_cli.py
wikipedia_cli-1.0.3.dist-info/DESCRIPTION.rst
wikipedia_cli-1.0.3.dist-info/METADATA
wikipedia_cli-1.0.3.dist-info/RECORD
wikipedia_cli-1.0.3.dist-info/WHEEL
wikipedia_cli-1.0.3.dist-info/entry_points.txt
wikipedia_cli-1.0.3.dist-info/metadata.json
wikipedia_cli-1.0.3.dist-info/top_level.txt
