Metadata-Version: 2.0
Name: wikipedia-cli
Version: 1.0.3
Summary: A command-line interface for fetching summaries of wikipedia pages.
Home-page: https://github.com/kalleroska/wikipedia-cli
Author: Kalle Saari
Author-email: kasaar2@gmail.com
License: MIT License
Keywords: wikipedia cli summary
Platform: UNKNOWN
Classifier: Programming Language :: Python
Classifier: Programming Language :: Python :: 3.5
Classifier: License :: OSI Approved :: MIT License
Classifier: Development Status :: 4 - Beta
Classifier: Topic :: Utilities
Classifier: Intended Audience :: Developers
Classifier: Environment :: Console
Requires-Dist: prompt-toolkit (==1.0.5)
Requires-Dist: wikipedia (==1.4.0)
